MANIFEST.in
README.md
VERSION
setup.cfg
setup.py
src/mlderes.dstoolkit.egg-info/PKG-INFO
src/mlderes.dstoolkit.egg-info/SOURCES.txt
src/mlderes.dstoolkit.egg-info/dependency_links.txt
src/mlderes.dstoolkit.egg-info/not-zip-safe
src/mlderes.dstoolkit.egg-info/top_level.txt
src/mlderes/dstoolkit/__init__.py
src/mlderes/dstoolkit/cleaning.py
src/mlderes/dstoolkit/constants.py
src/mlderes/dstoolkit/io.py
src/mlderes/dstoolkit/samples/__init__.py
src/mlderes/dstoolkit/samples/sample.py